{
  "inputs": [
    {
      "outputWeights": [
        0.81368506,
        -0.90374607,
        -0.19892195,
        -0.038907055,
        0.8188289,
        -0.458123,
        0.2540463,
        0.81906116,
        -0.090515055,
        -0.14820838,
        0.20542681
      ]
    },
    {
      "outputWeights": [
        -0.5237231,
        0.80535954,
        -0.21225967,
        0.052928183,
        0.049587816,
        -0.40136155,
        0.7317643,
        0.6336767,
        0.5031361,
        0.20183742,
        0.7617777
      ]
    },
    {
      "outputWeights": [
        0.5869074,
        -0.89566886,
        -0.6090751,
        -0.46533018,
        0.91801536,
        -0.3059205,
        0.16286765,
        0.5390544,
        -0.9960168,
        -0.0611504,
        -0.33161002
      ]
    },
    {
      "outputWeights": [
        -0.43886113,
        0.94409955,
        -0.6517941,
        0.76166517,
        0.8051867,
        -0.13014363,
        -0.5634798,
        -0.53456354,
        -0.9979174,
        -0.038339317,
        0.29810065
      ]
    },
    {
      "outputWeights": [
        -0.100014865,
        -0.45942286,
        0.62274075,
        0.39808318,
        -0.096733,
        -0.3241764,
        -0.57045597,
        0.75487876,
        -0.84810627,
        -0.450839,
        0.54121864
      ]
    }
  ],
  "hidden": [
    {
      "outputWeights": [
        -0.94809264
      ]
    },
    {
      "outputWeights": [
        -0.4906535
      ]
    },
    {
      "outputWeights": [
        -0.30325308
      ]
    },
    {
      "outputWeights": [
        -0.42983192
      ]
    },
    {
      "outputWeights": [
        0.2841591
      ]
    },
    {
      "outputWeights": [
        -0.3761384
      ]
    },
    {
      "outputWeights": [
        -0.4400332
      ]
    },
    {
      "outputWeights": [
        -0.3438065
      ]
    },
    {
      "outputWeights": [
        0.37043053
      ]
    },
    {
      "outputWeights": [
        -0.1521916
      ]
    },
    {
      "outputWeights": [
        -0.7334228
      ]
    }
  ],
  "outputs": [
    {}
  ],
  "Fitness": 0.0
}