{
  "inputs": [
    {
      "outputWeights": [
        0.36220714,
        0.11553478,
        -0.44301778,
        0.96353894,
        -0.37813005,
        0.16263463,
        -0.3875585,
        0.65114856,
        0.7729366,
        0.93410355,
        -0.65753156
      ]
    },
    {
      "outputWeights": [
        -0.14500201,
        0.7087692,
        -0.3863271,
        0.18839774,
        0.22283554,
        -0.61068624,
        -0.28770947,
        0.17392023,
        -0.16275194,
        -0.76722354,
        -0.3632085
      ]
    },
    {
      "outputWeights": [
        -0.288379,
        -0.040731356,
        0.56479967,
        0.3330439,
        0.21196932,
        0.72987634,
        -0.09079215,
        -0.86829746,
        0.33283436,
        -0.6160897,
        0.08586809
      ]
    },
    {
      "outputWeights": [
        -0.11768703,
        -0.40350193,
        -0.7936912,
        -0.5892531,
        -0.23623493,
        0.07596165,
        0.1273986,
        -0.06552102,
        -0.08968455,
        0.58214116,
        0.6249561
      ]
    },
    {
      "outputWeights": [
        -0.63945377,
        -0.9097128,
        -0.035590913,
        -0.96337587,
        -0.38493517,
        0.6647493,
        0.42578265,
        -0.26120666,
        0.77556866,
        -0.929211,
        0.32543504
      ]
    }
  ],
  "hidden": [
    {
      "outputWeights": [
        -0.27458435
      ]
    },
    {
      "outputWeights": [
        -0.5960862
      ]
    },
    {
      "outputWeights": [
        0.5977136
      ]
    },
    {
      "outputWeights": [
        -0.6012608
      ]
    },
    {
      "outputWeights": [
        0.28882605
      ]
    },
    {
      "outputWeights": [
        0.9506653
      ]
    },
    {
      "outputWeights": [
        -0.11743484
      ]
    },
    {
      "outputWeights": [
        -0.25805932
      ]
    },
    {
      "outputWeights": [
        0.64123404
      ]
    },
    {
      "outputWeights": [
        -0.39873078
      ]
    },
    {
      "outputWeights": [
        0.95855814
      ]
    }
  ],
  "outputs": [
    {}
  ],
  "Fitness": 0.0
}